{"version": 0.6, "generator": "Overpass API 0.7.62.11 87bfad18", "osm3s": {"timestamp_osm_base": "2026-04-24T16:37:21Z", "copyright": "The data included in this document is from www.openstreetmap.org. The data is made available under ODbL."}, "elements": [{"type": "node", "id": 2344922991, "lat": 42.5586004, "lon": 47.8734213, "tags": {"amenity": "fast_food", "name": "FoodShoop"}}, {"type": "node", "id": 2344923678, "lat": 42.5586362, "lon": 47.8736097}, {"type": "node", "id": 2344923679, "lat": 42.5583548, "lon": 47.8737736}, {"type": "node", "id": 2344923680, "lat": 42.5582673, "lon": 47.8734969}, {"type": "node", "id": 2344923681, "lat": 42.5585487, "lon": 47.873333}, {"type": "node", "id": 4078692882, "lat": 42.5675362, "lon": 47.8694738, "tags": {"addr:street": "\u0443\u043b\u0438\u0446\u0430 \u0413\u0430\u043c\u0438\u0434\u043e\u0432\u0430", "amenity": "cafe", "internet_access": "yes", "name": "\u041a\u0430\u043b\u0438\u0431\u0440\u0438"}}, {"type": "node", "id": 4207740191, "lat": 42.5690905, "lon": 47.856207, "tags": {"addr:street": "\u0443\u043b\u0438\u0446\u0430 \u041a\u043e\u0442\u0440\u043e\u0432\u0430", "name": "\u043c\u0430\u0433\u0430\u0437\u0438\u043d \"\u041c\u0430\u0433\u0430\u043c\"", "opening_hours": "Mo-Su 08:00-22:00", "shop": "department_store"}}, {"type": "node", "id": 4373211790, "lat": 42.5737269, "lon": 47.8616706, "tags": {"amenity": "bar", "name": "\u0421\u0443\u0448\u0438 \u0431\u0430\u0440", "name:ru": "\u0421\u0443\u0448\u0438 \u0431\u0430\u0440"}}, {"type": "node", "id": 4373259790, "lat": 42.5746631, "lon": 47.8622358, "tags": {"amenity": "fast_food", "cuisine": "kebab", "name": "\u0428\u0430\u0448\u043b\u044b\u043a-\u0448\u0430\u0443\u0440\u043c\u0430", "name:ru": "\u0428\u0430\u0448\u043b\u044b\u043a-\u0448\u0430\u0443\u0440\u043c\u0430"}}, {"type": "node", "id": 4373259791, "lat": 42.5744091, "lon": 47.8621884, "tags": {"amenity": "cafe", "name": "\u0421\u0438\u043c-\u0421\u0438\u043c", "name:ru": "\u0421\u0438\u043c-\u0421\u0438\u043c"}}, {"type": "node", "id": 4412152991, "lat": 42.5665676, "lon": 47.8718712, "tags": {"amenity": "cafe", "name": "\u0421\u041a\u0410\u0417\u041a\u0410", "name:ru": "\u0421\u041a\u0410\u0417\u041a\u0410"}}, {"type": "node", "id": 4567339081, "lat": 42.5551137, "lon": 47.8709177}, {"type": "node", "id": 4567339082, "lat": 42.5550722, "lon": 47.8709378}, {"type": "node", "id": 4567339083, "lat": 42.5551058, "lon": 47.8710263}, {"type": "node", "id": 4567339084, "lat": 42.5551414, "lon": 47.8710022}, {"type": "node", "id": 4632210989, "lat": 42.5809089, "lon": 47.8616481}, {"type": "node", "id": 4632210990, "lat": 42.5809403, "lon": 47.861761}, {"type": "node", "id": 4632210991, "lat": 42.5808682, "lon": 47.8617999}, {"type": "node", "id": 4632210992, "lat": 42.5808356, "lon": 47.8616913}, {"type": "node", "id": 4632210993, "lat": 42.580904, "lon": 47.8604035}, {"type": "node", "id": 4632210994, "lat": 42.5810019, "lon": 47.8607543}, {"type": "node", "id": 4632210995, "lat": 42.581142, "lon": 47.8606823}, {"type": "node", "id": 4632210996, "lat": 42.5812051, "lon": 47.8609085}, {"type": "node", "id": 4632210997, "lat": 42.5810759, "lon": 47.860975}, {"type": "node", "id": 4632210998, "lat": 42.5811546, "lon": 47.8612572}, {"type": "node", "id": 4632210999, "lat": 42.5810863, "lon": 47.8612923}, {"type": "node", "id": 4632211000, "lat": 42.5811159, "lon": 47.8613983}, {"type": "node", "id": 4632211001, "lat": 42.5812209, "lon": 47.8613442}, {"type": "node", "id": 4632211002, "lat": 42.5812544, "lon": 47.8614645}, {"type": "node", "id": 4632211003, "lat": 42.5806658, "lon": 47.8616128}, {"type": "node", "id": 4632211004, "lat": 42.5804285, "lon": 47.8607544}, {"type": "node", "id": 4632211005, "lat": 42.5806736, "lon": 47.8606284}, {"type": "node", "id": 4632211006, "lat": 42.5806477, "lon": 47.8605354}, {"type": "node", "id": 4632529699, "lat": 42.5512035, "lon": 47.8757776, "tags": {"name": "\u0420\u0443\u0441\u043b\u0430\u043d", "name:ru": "\u0420\u0443\u0441\u043b\u0430\u043d", "shop": "supermarket"}}, {"type": "node", "id": 4632529700, "lat": 42.5515215, "lon": 47.8785097, "tags": {"amenity": "pharmacy"}}, {"type": "node", "id": 4632529702, "lat": 42.5522282, "lon": 47.8769493, "tags": {"amenity": "pharmacy"}}, {"type": "node", "id": 4632530499, "lat": 42.5513458, "lon": 47.8767509, "tags": {"amenity": "pharmacy"}}, {"type": "node", "id": 4632530500, "lat": 42.5658893, "lon": 47.8654704, "tags": {"name": "\u0416\u0430\u0441\u043c\u0438\u043d", "name:ru": "\u0416\u0430\u0441\u043c\u0438\u043d", "shop": "supermarket"}}, {"type": "node", "id": 4632530501, "lat": 42.5685428, "lon": 47.8683109, "tags": {"shop": "convenience"}}, {"type": "node", "id": 4632538804, "lat": 42.5637932, "lon": 47.8651964, "tags": {"name": "\u0410\u0440\u0431\u0430\u0442", "name:ru": "\u0410\u0440\u0431\u0430\u0442", "shop": "convenience"}}, {"type": "node", "id": 4632538806, "lat": 42.5686202, "lon": 47.8635317, "tags": {"shop": "convenience"}}, {"type": "node", "id": 4632539791, "lat": 42.5668784, "lon": 47.865147, "tags": {"amenity": "cafe", "name": "7 \u043d\u0435\u0431\u043e", "name:ru": "7 \u043d\u0435\u0431\u043e"}}, {"type": "node", "id": 4632539792, "lat": 42.5679355, "lon": 47.8686328, "tags": {"amenity": "pharmacy"}}, {"type": "node", "id": 4632541091, "lat": 42.5526427, "lon": 47.8772487, "tags": {"amenity": "pharmacy"}}, {"type": "node", "id": 4632541092, "lat": 42.5616492, "lon": 47.8681565, "tags": {"check_date": "2023-12-31", "name": "\u0420\u0443\u0441\u043b\u0430\u043d", "name:ru": "\u0420\u0443\u0441\u043b\u0430\u043d", "opening_hours": "24/7", "shop": "supermarket"}}, {"type": "node", "id": 4632667689, "lat": 42.5588913, "lon": 47.8734642, "tags": {"name": "\u0416\u0430\u0441\u043c\u0438\u043d", "name:ru": "\u0416\u0430\u0441\u043c\u0438\u043d", "shop": "supermarket"}}, {"type": "node", "id": 5996335785, "lat": 42.5526956, "lon": 47.8754885, "tags": {"name": "\u0410\u0440\u0430\u0434\u0435\u0448", "shop": "department_store"}}, {"type": "node", "id": 5996335885, "lat": 42.5527662, "lon": 47.8754143, "tags": {"shop": "bakery"}}, {"type": "node", "id": 6724855343, "lat": 42.5734667, "lon": 47.8614637}, {"type": "node", "id": 6724855344, "lat": 42.5737317, "lon": 47.8615003}, {"type": "node", "id": 6724855345, "lat": 42.5736987, "lon": 47.8616975}, {"type": "node", "id": 6724855346, "lat": 42.5735236, "lon": 47.8618703}, {"type": "node", "id": 6724855347, "lat": 42.5734263, "lon": 47.861856}, {"type": "node", "id": 6898987426, "lat": 42.5736326, "lon": 47.8614866}, {"type": "node", "id": 7207779277, "lat": 42.5089882, "lon": 47.8409047}, {"type": "node", "id": 7207779278, "lat": 42.5088968, "lon": 47.8409677}, {"type": "node", "id": 7207779279, "lat": 42.5089073, "lon": 47.8410246}, {"type": "node", "id": 7207779280, "lat": 42.5090167, "lon": 47.8409494}, {"type": "node", "id": 7210802450, "lat": 42.5083666, "lon": 47.8401639}, {"type": "node", "id": 7210802451, "lat": 42.50826, "lon": 47.8402432}, {"type": "node", "id": 7210802452, "lat": 42.5082703, "lon": 47.8403505}, {"type": "node", "id": 7210802453, "lat": 42.5084216, "lon": 47.8402992}, {"type": "node", "id": 7300206487, "lat": 42.5531232, "lon": 47.8822213, "tags": {"addr:street": "\u0421\u043e\u0432\u0435\u0442\u0441\u043a\u0430\u044f \u0443\u043b\u0438\u0446\u0430", "name": "\u0410\u043f\u0435\u043b\u044c\u0441\u0438\u043d", "shop": "convenience"}}, {"type": "node", "id": 7300230185, "lat": 42.5531651, "lon": 47.8824002, "tags": {"addr:street": "\u0421\u043e\u0432\u0435\u0442\u0441\u043a\u0430\u044f \u0443\u043b\u0438\u0446\u0430", "name": "\u042e\u0436\u043d\u044b\u0439", "shop": "convenience"}}, {"type": "node", "id": 7954086786, "lat": 42.5757798, "lon": 47.8624954, "tags": {"amenity": "cafe", "name": "\u0421\u0430\u0444\u0430\u0440\u0438", "name:en": "Safari", "phone": "666664"}}, {"type": "node", "id": 8710004517, "lat": 42.561766, "lon": 47.8676794, "tags": {"air_conditioning": "yes", "amenity": "cafe", "check_date": "2023-12-31", "name": "\u0422\u0430\u0440\u0435\u043b\u043a\u0430", "name:en": "Tarelka", "opening_hours": "08:30-23:00", "payment:cash": "yes", "payment:mastercard": "yes", "payment:visa": "yes"}}, {"type": "node", "id": 8710005817, "lat": 42.5873967, "lon": 47.8768756, "tags": {"amenity": "cafe", "name": "\u0417\u043e\u043b\u043e\u0442\u0430\u044f \u0440\u044b\u0431\u043a\u0430", "name:en": "Zolotaya rybka"}}, {"type": "node", "id": 9079065717, "lat": 42.5640895, "lon": 47.8677402, "tags": {"amenity": "restaurant"}}, {"type": "node", "id": 9828541718, "lat": 42.4736309, "lon": 47.941311, "tags": {"amenity": "cafe", "cuisine": "grill;international;pizza;russian;turkish", "internet_access": "wlan", "name": "\u043a\u0430\u0444\u0435 \u0411\u0440\u0438\u0437", "name:en": "cafe Breeze"}}, {"type": "node", "id": 10868028852, "lat": 42.5742293, "lon": 47.8562365, "tags": {"name": "\u041d\u043e\u0440\u043c\u0430", "shop": "supermarket"}}, {"type": "node", "id": 11152563305, "lat": 42.5682606, "lon": 47.862951, "tags": {"amenity": "cafe", "cuisine": "beef_bowl;burger;chicken;friture;local;oriental;pizza", "name": "\u0421\u043b\u043e\u0439\u043a\u0430", "name:en": "Sloyka", "name:ru": "Sloyka", "opening_hours": "Mo-Su 10:00-23:00", "website": "https://sloyka-izberbash.ru/"}}, {"type": "node", "id": 11936925191, "lat": 42.5767386, "lon": 47.8622305}, {"type": "node", "id": 11936925192, "lat": 42.5766278, "lon": 47.8624581}, {"type": "node", "id": 11936925193, "lat": 42.5767813, "lon": 47.8623749}, {"type": "node", "id": 11936925194, "lat": 42.5765851, "lon": 47.8623135}, {"type": "node", "id": 13119737060, "lat": 42.5800172, "lon": 47.8837234}, {"type": "node", "id": 13119737061, "lat": 42.580193, "lon": 47.8839943}, {"type": "node", "id": 13119737062, "lat": 42.5796913, "lon": 47.8847131}, {"type": "node", "id": 13119737063, "lat": 42.5796222, "lon": 47.8846997}, {"type": "node", "id": 13119737066, "lat": 42.579634, "lon": 47.8842062}, {"type": "node", "id": 13119737072, "lat": 42.5796384, "lon": 47.8837506}, {"type": "node", "id": 13119737074, "lat": 42.5798572, "lon": 47.8839004}, {"type": "node", "id": 13119737075, "lat": 42.5796953, "lon": 47.8836751}, {"type": "node", "id": 13121496190, "lat": 42.5596398, "lon": 47.8753039, "tags": {"name": "\u041c\u0430\u0433\u043d\u0438\u0442", "shop": "supermarket"}}, {"type": "way", "id": 225737483, "nodes": [2344923681, 2344923680, 2344923679, 2344923678, 2344923681], "tags": {"amenity": "cinema", "building": "yes", "name": "CinemaHall"}}, {"type": "way", "id": 461196184, "nodes": [4567339081, 4567339082, 4567339083, 4567339084, 4567339081], "tags": {"addr:housenumber": "28", "addr:street": "\u041f\u0440\u043e\u043b\u0435\u0442\u0430\u0440\u0441\u043a\u0430\u044f \u0443\u043b\u0438\u0446\u0430", "landuse": "commercial", "name": "\u0413\u0430\u0441\u0442\u0440\u043e\u043d\u043e\u043c \"\u041c\u0415\u0427\u0422\u0410\""}}, {"type": "way", "id": 468748413, "nodes": [4632211006, 4632211005, 4632211004, 4632211003, 4632210992, 4632210991, 4632210990, 4632210989, 4632211002, 4632211001, 4632211000, 4632210999, 4632210998, 4632210997, 4632210996, 4632210995, 4632210994, 4632210993, 4632211006], "tags": {"addr:city": "\u0418\u0437\u0431\u0435\u0440\u0431\u0430\u0448", "addr:housenumber": "16", "addr:street": "\u0443\u043b\u0438\u0446\u0430 \u0410\u0437\u0438\u0437\u043e\u0432\u0430", "amenity": "theatre", "building": "yes", "name": "\u0414\u0430\u0440\u0433\u0438\u043d\u0441\u043a\u0438\u0439 \u0434\u0440\u0430\u043c\u0430\u0442\u0438\u0447\u0435\u0441\u043a\u0438\u0439 \u0442\u0435\u0430\u0442\u0440 \u0438\u043c. \u041e. \u0411\u0430\u0442\u044b\u0440\u0430\u044f"}}, {"type": "way", "id": 715548459, "nodes": [6724855343, 6898987426, 6724855344, 6724855345, 6724855346, 6724855347, 6724855343], "tags": {"addr:city": "\u0418\u0437\u0431\u0435\u0440\u0431\u0430\u0448", "addr:housenumber": "113", "addr:street": "\u0443\u043b\u0438\u0446\u0430 \u0411\u0443\u0439\u043d\u0430\u043a\u0441\u043a\u043e\u0433\u043e", "building": "yes", "name": "\u0413\u0423\u041c", "shop": "mall"}}, {"type": "way", "id": 772085858, "nodes": [7207779277, 7207779278, 7207779279, 7207779280, 7207779277], "tags": {"addr:housenumber": "26", "addr:street": "\u0443\u043b\u0438\u0446\u0430 \u0428\u0435\u0439\u0445\u0430 \u041c\u0430\u0433\u043e\u043c\u0435\u0434-\u0418\u043c\u0438\u043d\u0430 \u0414\u0435\u0439\u0431\u0443\u043a\u0441\u043a\u043e\u0433\u043e", "building": "yes", "shop": "bakery"}}, {"type": "way", "id": 772341611, "nodes": [7210802450, 7210802451, 7210802452, 7210802453, 7210802450], "tags": {"addr:housenumber": "18", "addr:street": "\u0443\u043b\u0438\u0446\u0430 \u0413\u0430\u043c\u0438\u0434\u043e\u0432\u0430", "building": "yes", "shop": "convenience"}}, {"type": "way", "id": 1287042982, "nodes": [11936925191, 11936925193, 11936925192, 11936925194, 11936925191], "tags": {"amenity": "restaurant", "cuisine": "georgian", "name": "\u0425\u0438\u043d\u043a\u0430\u043b\u044c\u043d\u0430\u044f"}}, {"type": "way", "id": 1427150832, "nodes": [13119737075, 13119737072, 13119737066, 13119737063, 13119737062, 13119737061, 13119737060, 13119737074, 13119737075], "tags": {"landuse": "commercial"}}]}